lexicontour/__init__.py
lexicontour/lexicontourfunctions.py
lexicontour-0.1.0.dist-info/METADATA
lexicontour-0.1.0.dist-info/WHEEL
lexicontour-0.1.0.dist-info/top_level.txt
lexicontour-0.1.0.dist-info/RECORD
