Metadata-Version: 2.1
Name: lexicontour
Version: 0.1.0
Summary: Extracts contours and text from given document. Draws bounding regions over the first page of the document.
Home-page: UNKNOWN
Author: Divija Kanumury, Vishal Varma Kovoru, Pravardhitha Myneni
License: MIT
Platform: UNKNOWN
